pipelining/__init__.py
pipelining/core/__init__.py
pipelining/core/multistep_stage.py
pipelining/core/pipeline.py
pipelining/core/stage.py
pipelining/util/__init__.py
pipelining/util/logger.py
pipelining_colemann-0.0.4.dist-info/METADATA
pipelining_colemann-0.0.4.dist-info/WHEEL
pipelining_colemann-0.0.4.dist-info/licenses/LICENSE
pipelining_colemann-0.0.4.dist-info/RECORD
