Metadata-Version: 2.4
Name: pipelining-colemann
Version: 0.0.4
Summary: A lightweight, object-orientated pipeline framework in Python
Project-URL: Documentation, https://github.com/colemannoah/pipelining#readme
Project-URL: Issues, https://github.com/colemannoah/pipelining/issues
Project-URL: Source, https://github.com/colemannoah/pipelining
Author-email: colemannoah <colemanmnoah@gmail.com>
License-Expression: MIT
License-File: LICENSE
Classifier: Development Status :: 4 - Beta
Classifier: Programming Language :: Python
Requires-Python: <3.14,>=3.10
Requires-Dist: rich
Requires-Dist: tqdm
